<?xml version="1.0" encoding="UTF-8" standalone="no"?><QuantumViewEvents><SubscriberID>gvreeman</SubscriberID><SubscriptionEvents><Name>Fineline_Out                       </Name><Number>05C988751BE8E94D                   </Number><DateRange><BeginDate>2012-05-14</BeginDate><EndDate>2012-05-14</EndDate></DateRange><SubscriptionFile><FileName>120514_144945001</FileName><StatusType><Code>R</Code><Description>Read</Description></StatusType><Delivery><PackageReferenceNumber><Value>105771</Value></PackageReferenceNumber><PackageReferenceNumber><Value>0</Value></PackageReferenceNumber><PackageReferenceNumber><Value>149207</Value></PackageReferenceNumber><ShipmentReferenceNumber><Value>105771</Value></ShipmentReferenceNumber><ShipperNumber>740101</ShipperNumber><TrackingNumber>1Z7401010346090243</TrackingNumber><Date>20120514</Date><Time>134900</Time><ActivityLocation><AddressArtifactFormat><PoliticalDivision2>BLOOMINGTON</PoliticalDivision2><PoliticalDivision1>IN</PoliticalDivision1><CountryCode>US</CountryCode></AddressArtifactFormat></ActivityLocation><DeliveryLocation><AddressArtifactFormat><StreetNumberLow>4850</StreetNumberLow><StreetPrefix>S</StreetPrefix><StreetName>STATE ROAD 446</StreetName><PoliticalDivision2>BLOOMINGTON</PoliticalDivision2><PoliticalDivision1>IN</PoliticalDivision1><CountryCode>US</CountryCode><PostcodePrimaryLow>47401</PostcodePrimaryLow><ResidentialAddressIndicator/></AddressArtifactFormat><Description>RECEIVER</Description><SignedForByName>LFWIS</SignedForByName></DeliveryLocation><BillToAccount><Option>01</Option><Number>740101</Number></BillToAccount></Delivery><Delivery><PackageReferenceNumber><Value>105771</Value></PackageReferenceNumber><PackageReferenceNumber><Value>0</Value></PackageReferenceNumber><PackageReferenceNumber><Value>149220</Value></PackageReferenceNumber><ShipmentReferenceNumber><Value>105771</Value></ShipmentReferenceNumber><ShipperNumber>740101</ShipperNumber><TrackingNumber>1Z7401010346399134</TrackingNumber><Date>20120514</Date><Time>140000</Time><ActivityLocation><AddressArtifactFormat><PoliticalDivision2>ANDERSON</PoliticalDivision2><PoliticalDivision1>IN</PoliticalDivision1><CountryCode>US</CountryCode></AddressArtifactFormat></ActivityLocation><DeliveryLocation><AddressArtifactFormat><StreetNumberLow>4306</StreetNumberLow><StreetName>MOUNDS</StreetName><StreetType>RD</StreetType><PoliticalDivision2>ANDERSON</PoliticalDivision2><PoliticalDivision1>IN</PoliticalDivision1><CountryCode>US</CountryCode><PostcodePrimaryLow>46017</PostcodePrimaryLow><ResidentialAddressIndicator/></AddressArtifactFormat><Description>OFFICE</Description><SignedForByName>ANDERSON</SignedForByName></DeliveryLocation><BillToAccount><Option>01</Option><Number>740101</Number></BillToAccount></Delivery><Delivery><PackageReferenceNumber><Value>105771</Value></PackageReferenceNumber><PackageReferenceNumber><Value>0</Value></PackageReferenceNumber><PackageReferenceNumber><Value>149207</Value></PackageReferenceNumber><ShipmentReferenceNumber><Value>105771</Value></ShipmentReferenceNumber><ShipperNumber>740101</ShipperNumber><TrackingNumber>1Z7401010347040616</TrackingNumber><Date>20120514</Date><Time>134900</Time><ActivityLocation><AddressArtifactFormat><PoliticalDivision2>BLOOMINGTON</PoliticalDivision2><PoliticalDivision1>IN</PoliticalDivision1><CountryCode>US</CountryCode></AddressArtifactFormat></ActivityLocation><DeliveryLocation><AddressArtifactFormat><StreetNumberLow>4850</StreetNumberLow><StreetPrefix>S</StreetPrefix><StreetName>STATE ROAD 446</StreetName><PoliticalDivision2>BLOOMINGTON</PoliticalDivision2><PoliticalDivision1>IN</PoliticalDivision1><CountryCode>US</CountryCode><PostcodePrimaryLow>47401</PostcodePrimaryLow><ResidentialAddressIndicator/></AddressArtifactFormat><Description>RECEIVER</Description><SignedForByName>LFWIS</SignedForByName></DeliveryLocation><BillToAccount><Option>01</Option><Number>740101</Number></BillToAccount></Delivery><Delivery><PackageReferenceNumber><Value>105771</Value></PackageReferenceNumber><PackageReferenceNumber><Value>0</Value></PackageReferenceNumber><PackageReferenceNumber><Value>149207</Value></PackageReferenceNumber><ShipmentReferenceNumber><Value>105771</Value></ShipmentReferenceNumber><ShipperNumber>740101</ShipperNumber><TrackingNumber>1Z7401010347128255</TrackingNumber><Date>20120514</Date><Time>134900</Time><ActivityLocation><AddressArtifactFormat><PoliticalDivision2>BLOOMINGTON</PoliticalDivision2><PoliticalDivision1>IN</PoliticalDivision1><CountryCode>US</CountryCode></AddressArtifactFormat></ActivityLocation><DeliveryLocation><AddressArtifactFormat><StreetNumberLow>4850</StreetNumberLow><StreetPrefix>S</StreetPrefix><StreetName>STATE ROAD 446</StreetName><PoliticalDivision2>BLOOMINGTON</PoliticalDivision2><PoliticalDivision1>IN</PoliticalDivision1><CountryCode>US</CountryCode><PostcodePrimaryLow>47401</PostcodePrimaryLow><ResidentialAddressIndicator/></AddressArtifactFormat><Description>RECEIVER</Description><SignedForByName>LFWIS</SignedForByName></DeliveryLocation><BillToAccount><Option>01</Option><Number>740101</Number></BillToAccount></Delivery><Delivery><PackageReferenceNumber><Value>105771</Value></PackageReferenceNumber><PackageReferenceNumber><Value>0</Value></PackageReferenceNumber><PackageReferenceNumber><Value>149220</Value></PackageReferenceNumber><ShipmentReferenceNumber><Value>105771</Value></ShipmentReferenceNumber><ShipperNumber>740101</ShipperNumber><TrackingNumber>1Z7401010347905745</TrackingNumber><Date>20120514</Date><Time>140000</Time><ActivityLocation><AddressArtifactFormat><PoliticalDivision2>ANDERSON</PoliticalDivision2><PoliticalDivision1>IN</PoliticalDivision1><CountryCode>US</CountryCode></AddressArtifactFormat></ActivityLocation><DeliveryLocation><AddressArtifactFormat><StreetNumberLow>4306</StreetNumberLow><StreetName>MOUNDS</StreetName><StreetType>RD</StreetType><PoliticalDivision2>ANDERSON</PoliticalDivision2><PoliticalDivision1>IN</PoliticalDivision1><CountryCode>US</CountryCode><PostcodePrimaryLow>46017</PostcodePrimaryLow><ResidentialAddressIndicator/></AddressArtifactFormat><Description>OFFICE</Description><SignedForByName>ANDERSON</SignedForByName></DeliveryLocation><BillToAccount><Option>01</Option><Number>740101</Number></BillToAccount></Delivery><Delivery><PackageReferenceNumber><Value>105771</Value></PackageReferenceNumber><PackageReferenceNumber><Value>0</Value></PackageReferenceNumber><PackageReferenceNumber><Value>149207</Value></PackageReferenceNumber><ShipmentReferenceNumber><Value>105771</Value></ShipmentReferenceNumber><ShipperNumber>740101</ShipperNumber><TrackingNumber>1Z7401010348303661</TrackingNumber><Date>20120514</Date><Time>134900</Time><ActivityLocation><AddressArtifactFormat><PoliticalDivision2>BLOOMINGTON</PoliticalDivision2><PoliticalDivision1>IN</PoliticalDivision1><CountryCode>US</CountryCode></AddressArtifactFormat></ActivityLocation><DeliveryLocation><AddressArtifactFormat><StreetNumberLow>4850</StreetNumberLow><StreetPrefix>S</StreetPrefix><StreetName>STATE ROAD 446</StreetName><PoliticalDivision2>BLOOMINGTON</PoliticalDivision2><PoliticalDivision1>IN</PoliticalDivision1><CountryCode>US</CountryCode><PostcodePrimaryLow>47401</PostcodePrimaryLow><ResidentialAddressIndicator/></AddressArtifactFormat><Description>RECEIVER</Description><SignedForByName>LFWIS</SignedForByName></DeliveryLocation><BillToAccount><Option>01</Option><Number>740101</Number></BillToAccount></Delivery><Delivery><PackageReferenceNumber><Value>105771</Value></PackageReferenceNumber><PackageReferenceNumber><Value>0</Value></PackageReferenceNumber><PackageReferenceNumber><Value>149207</Value></PackageReferenceNumber><ShipmentReferenceNumber><Value>105771</Value></ShipmentReferenceNumber><ShipperNumber>740101</ShipperNumber><TrackingNumber>1Z7401010348592206</TrackingNumber><Date>20120514</Date><Time>134900</Time><ActivityLocation><AddressArtifactFormat><PoliticalDivision2>BLOOMINGTON</PoliticalDivision2><PoliticalDivision1>IN</PoliticalDivision1><CountryCode>US</CountryCode></AddressArtifactFormat></ActivityLocation><DeliveryLocation><AddressArtifactFormat><StreetNumberLow>4850</StreetNumberLow><StreetPrefix>S</StreetPrefix><StreetName>STATE ROAD 446</StreetName><PoliticalDivision2>BLOOMINGTON</PoliticalDivision2><PoliticalDivision1>IN</PoliticalDivision1><CountryCode>US</CountryCode><PostcodePrimaryLow>47401</PostcodePrimaryLow><ResidentialAddressIndicator/></AddressArtifactFormat><Description>RECEIVER</Description><SignedForByName>LFWIS</SignedForByName></DeliveryLocation><BillToAccount><Option>01</Option><Number>740101</Number></BillToAccount></Delivery><Delivery><PackageReferenceNumber><Value>105771</Value></PackageReferenceNumber><PackageReferenceNumber><Value>0</Value></PackageReferenceNumber><PackageReferenceNumber><Value>149207</Value></PackageReferenceNumber><ShipmentReferenceNumber><Value>105771</Value></ShipmentReferenceNumber><ShipperNumber>740101</ShipperNumber><TrackingNumber>1Z7401010348692474</TrackingNumber><Date>20120514</Date><Time>134900</Time><ActivityLocation><AddressArtifactFormat><PoliticalDivision2>BLOOMINGTON</PoliticalDivision2><PoliticalDivision1>IN</PoliticalDivision1><CountryCode>US</CountryCode></AddressArtifactFormat></ActivityLocation><DeliveryLocation><AddressArtifactFormat><StreetNumberLow>4850</StreetNumberLow><StreetPrefix>S</StreetPrefix><StreetName>STATE ROAD 446</StreetName><PoliticalDivision2>BLOOMINGTON</PoliticalDivision2><PoliticalDivision1>IN</PoliticalDivision1><CountryCode>US</CountryCode><PostcodePrimaryLow>47401</PostcodePrimaryLow><ResidentialAddressIndicator/></AddressArtifactFormat><Description>RECEIVER</Description><SignedForByName>LFWIS</SignedForByName></DeliveryLocation><BillToAccount><Option>01</Option><Number>740101</Number></BillToAccount></Delivery><Delivery><PackageReferenceNumber><Value>105771</Value></PackageReferenceNumber><PackageReferenceNumber><Value>0</Value></PackageReferenceNumber><PackageReferenceNumber><Value>149207</Value></PackageReferenceNumber><ShipmentReferenceNumber><Value>105771</Value></ShipmentReferenceNumber><ShipperNumber>740101</ShipperNumber><TrackingNumber>1Z7401010348722422</TrackingNumber><Date>20120514</Date><Time>134900</Time><ActivityLocation><AddressArtifactFormat><PoliticalDivision2>BLOOMINGTON</PoliticalDivision2><PoliticalDivision1>IN</PoliticalDivision1><CountryCode>US</CountryCode></AddressArtifactFormat></ActivityLocation><DeliveryLocation><AddressArtifactFormat><StreetNumberLow>4850</StreetNumberLow><StreetPrefix>S</StreetPrefix><StreetName>STATE ROAD 446</StreetName><PoliticalDivision2>BLOOMINGTON</PoliticalDivision2><PoliticalDivision1>IN</PoliticalDivision1><CountryCode>US</CountryCode><PostcodePrimaryLow>47401</PostcodePrimaryLow><ResidentialAddressIndicator/></AddressArtifactFormat><Description>RECEIVER</Description><SignedForByName>LFWIS</SignedForByName></DeliveryLocation><BillToAccount><Option>01</Option><Number>740101</Number></BillToAccount></Delivery><Delivery><PackageReferenceNumber><Value>105771</Value></PackageReferenceNumber><PackageReferenceNumber><Value>0</Value></PackageReferenceNumber><PackageReferenceNumber><Value>149207</Value></PackageReferenceNumber><ShipmentReferenceNumber><Value>105771</Value></ShipmentReferenceNumber><ShipperNumber>740101</ShipperNumber><TrackingNumber>1Z7401010348753630</TrackingNumber><Date>20120514</Date><Time>134900</Time><ActivityLocation><AddressArtifactFormat><PoliticalDivision2>BLOOMINGTON</PoliticalDivision2><PoliticalDivision1>IN</PoliticalDivision1><CountryCode>US</CountryCode></AddressArtifactFormat></ActivityLocation><DeliveryLocation><AddressArtifactFormat><StreetNumberLow>4850</StreetNumberLow><StreetPrefix>S</StreetPrefix><StreetName>STATE ROAD 446</StreetName><PoliticalDivision2>BLOOMINGTON</PoliticalDivision2><PoliticalDivision1>IN</PoliticalDivision1><CountryCode>US</CountryCode><PostcodePrimaryLow>47401</PostcodePrimaryLow><ResidentialAddressIndicator/></AddressArtifactFormat><Description>RECEIVER</Description><SignedForByName>LFWIS</SignedForByName></DeliveryLocation><BillToAccount><Option>01</Option><Number>740101</Number></BillToAccount></Delivery><Delivery><PackageReferenceNumber><Value>105771</Value></PackageReferenceNumber><PackageReferenceNumber><Value>0</Value></PackageReferenceNumber><PackageReferenceNumber><Value>149220</Value></PackageReferenceNumber><ShipmentReferenceNumber><Value>105771</Value></ShipmentReferenceNumber><ShipperNumber>740101</ShipperNumber><TrackingNumber>1Z7401010348859160</TrackingNumber><Date>20120514</Date><Time>140000</Time><ActivityLocation><AddressArtifactFormat><PoliticalDivision2>ANDERSON</PoliticalDivision2><PoliticalDivision1>IN</PoliticalDivision1><CountryCode>US</CountryCode></AddressArtifactFormat></ActivityLocation><DeliveryLocation><AddressArtifactFormat><StreetNumberLow>4306</StreetNumberLow><StreetName>MOUNDS</StreetName><StreetType>RD</StreetType><PoliticalDivision2>ANDERSON</PoliticalDivision2><PoliticalDivision1>IN</PoliticalDivision1><CountryCode>US</CountryCode><PostcodePrimaryLow>46017</PostcodePrimaryLow><ResidentialAddressIndicator/></AddressArtifactFormat><Description>OFFICE</Description><SignedForByName>ANDERSON</SignedForByName></DeliveryLocation><BillToAccount><Option>01</Option><Number>740101</Number></BillToAccount></Delivery><Delivery><PackageReferenceNumber><Value>105771</Value></PackageReferenceNumber><PackageReferenceNumber><Value>0</Value></PackageReferenceNumber><PackageReferenceNumber><Value>149220</Value></PackageReferenceNumber><ShipmentReferenceNumber><Value>105771</Value></ShipmentReferenceNumber><ShipperNumber>740101</ShipperNumber><TrackingNumber>1Z7401010348913752</TrackingNumber><Date>20120514</Date><Time>140000</Time><ActivityLocation><AddressArtifactFormat><PoliticalDivision2>ANDERSON</PoliticalDivision2><PoliticalDivision1>IN</PoliticalDivision1><CountryCode>US</CountryCode></AddressArtifactFormat></ActivityLocation><DeliveryLocation><AddressArtifactFormat><StreetNumberLow>4306</StreetNumberLow><StreetName>MOUNDS</StreetName><StreetType>RD</StreetType><PoliticalDivision2>ANDERSON</PoliticalDivision2><PoliticalDivision1>IN</PoliticalDivision1><CountryCode>US</CountryCode><PostcodePrimaryLow>46017</PostcodePrimaryLow><ResidentialAddressIndicator/></AddressArtifactFormat><Description>OFFICE</Description><SignedForByName>ANDERSON</SignedForByName></DeliveryLocation><BillToAccount><Option>01</Option><Number>740101</Number></BillToAccount></Delivery></SubscriptionFile></SubscriptionEvents></QuantumViewEvents>